LICENSE.md
README.md
setup.cfg
setup.py
ezdev/__init__.py
ezdev/enums.py
ezdev/errors.py
ezdev/main.py
ezdev/requirements.txt
ezdev/requirements_dev.txt
ezdev/requirements_extend.txt
ezdev/requirements_osx.txt
ezdev.egg-info/PKG-INFO
ezdev.egg-info/SOURCES.txt
ezdev.egg-info/dependency_links.txt
ezdev.egg-info/entry_points.txt
ezdev.egg-info/requires.txt
ezdev.egg-info/top_level.txt
ezdev/commands/__init__.py
ezdev/commands/gitlab_runner.py
ezdev/utils/__init__.py
ezdev/utils/env_reader.py
ezdev/utils/files.py
ezdev/utils/j2.py
ezdev/utils/log.py
ezdev/utils/output.py